conditional_model_reliance/__init__.py
conditional_model_reliance/cmr.py
conditional_model_reliance-0.0.2.dist-info/METADATA
conditional_model_reliance-0.0.2.dist-info/WHEEL
conditional_model_reliance-0.0.2.dist-info/licenses/LICENSE
conditional_model_reliance-0.0.2.dist-info/RECORD
